{
  "key": "van_Dis_2020",
  "publication": {
    "doi": "10.1001/jamapsychiatry.2019.3986"
  },
  "data": {
    "url": "https://osf.io/4d9tu/",
    "n_records": 9128,
    "n_records_included": 72,
    "concepts": {
      "included": [
        {
          "id": "https://openalex.org/C15744967",
          "wikidata": "https://www.wikidata.org/wiki/Q9418",
          "display_name": "Psychology",
          "level": 0,
          "score": 0.5001807
        },
        {
          "id": "https://openalex.org/C71924100",
          "wikidata": "https://www.wikidata.org/wiki/Q11190",
          "display_name": "Medicine",
          "level": 0,
          "score": 0.3354233
        }
      ]
    }
  }
}