{
  "id": "https://openalex.org/W2792169531",
  "doi": "https://doi.org/10.1016/j.envint.2017.12.032",
  "title": "Human and animal evidence of potential transgenerational inheritance of health effects: An evidence map and state-of-the-science evaluation",
  "display_name": "Human and animal evidence of potential transgenerational inheritance of health effects: An evidence map and state-of-the-science evaluation",
  "publication_year": 2018,
  "publication_date": "2018-06-01",
  "ids": {
    "openalex": "https://openalex.org/W2792169531",
    "doi": "https://doi.org/10.1016/j.envint.2017.12.032",
    "mag": "2792169531",
    "pmid": "https://pubmed.ncbi.nlm.nih.gov/29549716"
  },
  "primary_location": {
    "is_oa": false,
    "landing_page_url": "https://doi.org/10.1016/j.envint.2017.12.032",
    "pdf_url": null,
    "source": {
      "id": "https://openalex.org/S143381477",
      "display_name": "Environment International",
      "issn_l": "0160-4120",
      "issn": [
        "0160-4120",
        "1873-6750"
      ],
      "host_organization": "https://openalex.org/P4310320990",
      "host_organization_name": "Elsevier BV",
      "type": "journal"
    },
    "license": null,
    "version": null
  },
  "host_venue": {
    "id": "https://openalex.org/S143381477",
    "issn_l": "0160-4120",
    "issn": [
      "0160-4120",
      "1873-6750"
    ],
    "display_name": "Environment International",
    "publisher": "Elsevier BV",
    "type": "journal",
    "url": null,
    "is_oa": false,
    "version": null,
    "license": null
  },
  "type": "journal-article",
  "open_access": {
    "is_oa": false,
    "oa_status": "closed",
    "oa_url": null,
    "any_repository_has_fulltext": false
  },
  "authorships": [
    {
      "author_position": "first",
      "author": {
        "id": "https://openalex.org/A4331552621",
        "display_name": "Vickie R. Walker",
        "orcid": null
      },
      "institutions": [
        {
          "id": "https://openalex.org/I1299303238",
          "display_name": "National Institutes of Health",
          "ror": "https://ror.org/01cwqze88",
          "country_code": "US",
          "type": "government"
        }
      ],
      "is_corresponding": false,
      "raw_affiliation_string": ""
    },
    {
      "author_position": "middle",
      "author": {
        "id": "https://openalex.org/A4349590080",
        "display_name": "Abee L. Boyles",
        "orcid": null
      },
      "institutions": [
        {
          "id": "https://openalex.org/I1299303238",
          "display_name": "National Institutes of Health",
          "ror": "https://ror.org/01cwqze88",
          "country_code": "US",
          "type": "government"
        }
      ],
      "is_corresponding": false,
      "raw_affiliation_string": ""
    },
    {
      "author_position": "middle",
      "author": {
        "id": "https://openalex.org/A4346683615",
        "display_name": "Katherine E. Pelch",
        "orcid": null
      },
      "institutions": [
        {
          "id": "https://openalex.org/I1299303238",
          "display_name": "National Institutes of Health",
          "ror": "https://ror.org/01cwqze88",
          "country_code": "US",
          "type": "government"
        }
      ],
      "is_corresponding": false,
      "raw_affiliation_string": ""
    },
    {
      "author_position": "middle",
      "author": {
        "id": "https://openalex.org/A4333324592",
        "display_name": "Stephanie Holmgren",
        "orcid": null
      },
      "institutions": [
        {
          "id": "https://openalex.org/I1299022934",
          "display_name": "United States Department of Health and Human Services",
          "ror": "https://ror.org/033jnv181",
          "country_code": "US",
          "type": "government"
        }
      ],
      "is_corresponding": false,
      "raw_affiliation_string": "Office of Data Science, NIEHS, NIH, DHHS, Research Triangle Park, NC, USA"
    },
    {
      "author_position": "middle",
      "author": {
        "id": "https://openalex.org/A4359435577",
        "display_name": "Andrew A. Shapiro",
        "orcid": null
      },
      "institutions": [
        {
          "id": null,
          "display_name": "Program Operations Branch, DNTP, NIEHS, NIH, DHHS, Research Triangle Park, NC, USA",
          "ror": null,
          "country_code": null,
          "type": null
        }
      ],
      "is_corresponding": false,
      "raw_affiliation_string": "Program Operations Branch, DNTP, NIEHS, NIH, DHHS, Research Triangle Park, NC, USA"
    },
    {
      "author_position": "middle",
      "author": {
        "id": "https://openalex.org/A4349018292",
        "display_name": "Chad R. Blystone",
        "orcid": null
      },
      "institutions": [
        {
          "id": null,
          "display_name": "Toxicology Branch, DNTP, NIEHS, NIH, DHHS, Research Triangle Park, NC, USA.",
          "ror": null,
          "country_code": null,
          "type": null
        }
      ],
      "is_corresponding": false,
      "raw_affiliation_string": "Toxicology Branch, DNTP, NIEHS, NIH, DHHS, Research Triangle Park, NC, USA."
    },
    {
      "author_position": "middle",
      "author": {
        "id": "https://openalex.org/A4346429701",
        "display_name": "Michael J. DeVito",
        "orcid": null
      },
      "institutions": [
        {
          "id": "https://openalex.org/I1309191912",
          "display_name": "Research Triangle Park Foundation",
          "ror": "https://ror.org/03eqttr49",
          "country_code": "US",
          "type": "nonprofit"
        }
      ],
      "is_corresponding": false,
      "raw_affiliation_string": "NTP Laboratory, DNTP, NIEHS, NIH, DHHS, Research Triangle Park, NC, USA"
    },
    {
      "author_position": "middle",
      "author": {
        "id": "https://openalex.org/A4343374914",
        "display_name": "Retha R. Newbold",
        "orcid": null
      },
      "institutions": [
        {
          "id": "https://openalex.org/I1299022934",
          "display_name": "United States Department of Health and Human Services",
          "ror": "https://ror.org/033jnv181",
          "country_code": "US",
          "type": "government"
        }
      ],
      "is_corresponding": false,
      "raw_affiliation_string": "Researcher Emeritus, DNTP, NIEHS, NIH, DHHS, Research Triangle Park, NC, USA"
    },
    {
      "author_position": "middle",
      "author": {
        "id": "https://openalex.org/A2698030492",
        "display_name": "Robyn B. Blain",
        "orcid": null
      },
      "institutions": [
        {
          "id": "https://openalex.org/I1309191912",
          "display_name": "Research Triangle Park Foundation",
          "ror": "https://ror.org/03eqttr49",
          "country_code": "US",
          "type": "nonprofit"
        }
      ],
      "is_corresponding": false,
      "raw_affiliation_string": "ICF, Research Triangle Park, NC, USA."
    },
    {
      "author_position": "middle",
      "author": {
        "id": "https://openalex.org/A4332530888",
        "display_name": "Pamela Hartman",
        "orcid": null
      },
      "institutions": [
        {
          "id": "https://openalex.org/I1309191912",
          "display_name": "Research Triangle Park Foundation",
          "ror": "https://ror.org/03eqttr49",
          "country_code": "US",
          "type": "nonprofit"
        }
      ],
      "is_corresponding": false,
      "raw_affiliation_string": "ICF, Research Triangle Park, NC, USA."
    },
    {
      "author_position": "middle",
      "author": {
        "id": "https://openalex.org/A4356569659",
        "display_name": "Kristina A. Thayer",
        "orcid": null
      },
      "institutions": [
        {
          "id": "https://openalex.org/I1299303238",
          "display_name": "National Institutes of Health",
          "ror": "https://ror.org/01cwqze88",
          "country_code": "US",
          "type": "government"
        }
      ],
      "is_corresponding": false,
      "raw_affiliation_string": ""
    },
    {
      "author_position": "last",
      "author": {
        "id": "https://openalex.org/A4339951073",
        "display_name": "Andrew A. Rooney",
        "orcid": null
      },
      "institutions": [
        {
          "id": "https://openalex.org/I1299303238",
          "display_name": "National Institutes of Health",
          "ror": "https://ror.org/01cwqze88",
          "country_code": "US",
          "type": "government"
        }
      ],
      "is_corresponding": false,
      "raw_affiliation_string": ""
    }
  ],
  "cited_by_count": 17,
  "biblio": {
    "volume": "115",
    "issue": null,
    "first_page": "48",
    "last_page": "69"
  },
  "is_retracted": false,
  "is_paratext": false,
  "concepts": [
    {
      "id": "https://openalex.org/C184151982",
      "wikidata": "https://www.wikidata.org/wiki/Q7834236",
      "display_name": "Transgenerational epigenetics",
      "level": 4,
      "score": "0.75204587"
    },
    {
      "id": "https://openalex.org/C125370674",
      "wikidata": "https://www.wikidata.org/wiki/Q1527480",
      "display_name": "Stressor",
      "level": 2,
      "score": "0.55658484"
    },
    {
      "id": "https://openalex.org/C99454951",
      "wikidata": "https://www.wikidata.org/wiki/Q932068",
      "display_name": "Environmental health",
      "level": 1,
      "score": "0.47069764"
    },
    {
      "id": "https://openalex.org/C166052673",
      "wikidata": "https://www.wikidata.org/wiki/Q83021",
      "display_name": "Empirical evidence",
      "level": 2,
      "score": "0.4705066"
    },
    {
      "id": "https://openalex.org/C2780902518",
      "wikidata": "https://www.wikidata.org/wiki/Q6033780",
      "display_name": "Inheritance (genetic algorithm)",
      "level": 3,
      "score": "0.44997722"
    },
    {
      "id": "https://openalex.org/C94124525",
      "wikidata": "https://www.wikidata.org/wiki/Q912550",
      "display_name": "Categorization",
      "level": 2,
      "score": "0.42800784"
    },
    {
      "id": "https://openalex.org/C138816342",
      "wikidata": "https://www.wikidata.org/wiki/Q189603",
      "display_name": "Public health",
      "level": 2,
      "score": "0.4267795"
    },
    {
      "id": "https://openalex.org/C148482608",
      "wikidata": "https://www.wikidata.org/wiki/Q17007018",
      "display_name": "Clinical study design",
      "level": 3,
      "score": "0.42065167"
    },
    {
      "id": "https://openalex.org/C141330323",
      "wikidata": "https://www.wikidata.org/wiki/Q2354820",
      "display_name": "Evidence-based practice",
      "level": 3,
      "score": "0.41376236"
    },
    {
      "id": "https://openalex.org/C15744967",
      "wikidata": "https://www.wikidata.org/wiki/Q9418",
      "display_name": "Psychology",
      "level": 0,
      "score": "0.3768614"
    },
    {
      "id": "https://openalex.org/C71924100",
      "wikidata": "https://www.wikidata.org/wiki/Q11190",
      "display_name": "Medicine",
      "level": 0,
      "score": "0.36688033"
    },
    {
      "id": "https://openalex.org/C86803240",
      "wikidata": "https://www.wikidata.org/wiki/Q420",
      "display_name": "Biology",
      "level": 0,
      "score": "0.305106"
    },
    {
      "id": "https://openalex.org/C112672928",
      "wikidata": "https://www.wikidata.org/wiki/Q239526",
      "display_name": "Offspring",
      "level": 3,
      "score": "0.27530646"
    },
    {
      "id": "https://openalex.org/C70410870",
      "wikidata": "https://www.wikidata.org/wiki/Q199906",
      "display_name": "Clinical psychology",
      "level": 1,
      "score": "0.2216174"
    },
    {
      "id": "https://openalex.org/C54355233",
      "wikidata": "https://www.wikidata.org/wiki/Q7162",
      "display_name": "Genetics",
      "level": 1,
      "score": "0.16471791"
    },
    {
      "id": "https://openalex.org/C142724271",
      "wikidata": "https://www.wikidata.org/wiki/Q7208",
      "display_name": "Pathology",
      "level": 1,
      "score": "0.15027317"
    },
    {
      "id": "https://openalex.org/C535046627",
      "wikidata": "https://www.wikidata.org/wiki/Q30612",
      "display_name": "Clinical trial",
      "level": 2,
      "score": "0.14408496"
    },
    {
      "id": "https://openalex.org/C2779234561",
      "wikidata": "https://www.wikidata.org/wiki/Q11995",
      "display_name": "Pregnancy",
      "level": 2,
      "score": "0.12983635"
    },
    {
      "id": "https://openalex.org/C41008148",
      "wikidata": "https://www.wikidata.org/wiki/Q21198",
      "display_name": "Computer science",
      "level": 0,
      "score": "0.12563875"
    },
    {
      "id": "https://openalex.org/C204787440",
      "wikidata": "https://www.wikidata.org/wiki/Q188504",
      "display_name": "Alternative medicine",
      "level": 2,
      "score": "0.092209935"
    },
    {
      "id": "https://openalex.org/C138885662",
      "wikidata": "https://www.wikidata.org/wiki/Q5891",
      "display_name": "Philosophy",
      "level": 0,
      "score": "0.0"
    },
    {
      "id": "https://openalex.org/C111472728",
      "wikidata": "https://www.wikidata.org/wiki/Q9471",
      "display_name": "Epistemology",
      "level": 1,
      "score": "0.0"
    },
    {
      "id": "https://openalex.org/C154945302",
      "wikidata": "https://www.wikidata.org/wiki/Q11660",
      "display_name": "Artificial intelligence",
      "level": 1,
      "score": "0.0"
    },
    {
      "id": "https://openalex.org/C104317684",
      "wikidata": "https://www.wikidata.org/wiki/Q7187",
      "display_name": "Gene",
      "level": 2,
      "score": "0.0"
    }
  ],
  "mesh": [
    {
      "descriptor_ui": "D035843",
      "descriptor_name": "Biomedical Research",
      "qualifier_ui": "",
      "qualifier_name": null,
      "is_major_topic": true
    },
    {
      "descriptor_ui": "D016208",
      "descriptor_name": "Databases, Factual",
      "qualifier_ui": "",
      "qualifier_name": null,
      "is_major_topic": true
    },
    {
      "descriptor_ui": "D004781",
      "descriptor_name": "Environmental Exposure",
      "qualifier_ui": "Q000032",
      "qualifier_name": "analysis",
      "is_major_topic": true
    },
    {
      "descriptor_ui": "D000818",
      "descriptor_name": "Animals",
      "qualifier_ui": "",
      "qualifier_name": null,
      "is_major_topic": false
    },
    {
      "descriptor_ui": "D035843",
      "descriptor_name": "Biomedical Research",
      "qualifier_ui": "Q000592",
      "qualifier_name": "standards",
      "is_major_topic": false
    },
    {
      "descriptor_ui": "D035843",
      "descriptor_name": "Biomedical Research",
      "qualifier_ui": "Q000379",
      "qualifier_name": "methods",
      "is_major_topic": false
    },
    {
      "descriptor_ui": "D004781",
      "descriptor_name": "Environmental Exposure",
      "qualifier_ui": "",
      "qualifier_name": null,
      "is_major_topic": false
    },
    {
      "descriptor_ui": "D005260",
      "descriptor_name": "Female",
      "qualifier_ui": "",
      "qualifier_name": null,
      "is_major_topic": false
    },
    {
      "descriptor_ui": "D006801",
      "descriptor_name": "Humans",
      "qualifier_ui": "",
      "qualifier_name": null,
      "is_major_topic": false
    },
    {
      "descriptor_ui": "D008297",
      "descriptor_name": "Male",
      "qualifier_ui": "",
      "qualifier_name": null,
      "is_major_topic": false
    },
    {
      "descriptor_ui": "D018811",
      "descriptor_name": "Maternal Exposure",
      "qualifier_ui": "",
      "qualifier_name": null,
      "is_major_topic": false
    },
    {
      "descriptor_ui": "D018812",
      "descriptor_name": "Paternal Exposure",
      "qualifier_ui": "",
      "qualifier_name": null,
      "is_major_topic": false
    },
    {
      "descriptor_ui": "D011247",
      "descriptor_name": "Pregnancy",
      "qualifier_ui": "",
      "qualifier_name": null,
      "is_major_topic": false
    },
    {
      "descriptor_ui": "D011297",
      "descriptor_name": "Prenatal Exposure Delayed Effects",
      "qualifier_ui": "",
      "qualifier_name": null,
      "is_major_topic": false
    }
  ],
  "locations": [
    {
      "is_oa": false,
      "landing_page_url": "https://doi.org/10.1016/j.envint.2017.12.032",
      "pdf_url": null,
      "source": {
        "id": "https://openalex.org/S143381477",
        "display_name": "Environment International",
        "issn_l": "0160-4120",
        "issn": [
          "0160-4120",
          "1873-6750"
        ],
        "host_organization": "https://openalex.org/P4310320990",
        "host_organization_name": "Elsevier BV",
        "type": "journal"
      },
      "license": null,
      "version": null
    }
  ],
  "best_oa_location": null,
  "alternate_host_venues": [
    {
      "id": "https://openalex.org/S143381477",
      "display_name": "Environment International",
      "type": "journal",
      "url": null,
      "is_oa": false,
      "version": null,
      "license": null
    }
  ],
  "referenced_works": [
    "https://openalex.org/W396736222",
    "https://openalex.org/W1483349607",
    "https://openalex.org/W1497732779",
    "https://openalex.org/W1502523862",
    "https://openalex.org/W1566751645",
    "https://openalex.org/W1680172220",
    "https://openalex.org/W1837809897",
    "https://openalex.org/W1964990421",
    "https://openalex.org/W1968562138",
    "https://openalex.org/W1971708895",
    "https://openalex.org/W1974941850",
    "https://openalex.org/W1974982848",
    "https://openalex.org/W1976935056",
    "https://openalex.org/W1986667734",
    "https://openalex.org/W1990370417",
    "https://openalex.org/W1997388146",
    "https://openalex.org/W1999414155",
    "https://openalex.org/W2001070286",
    "https://openalex.org/W2002578132",
    "https://openalex.org/W2007427663",
    "https://openalex.org/W2008151232",
    "https://openalex.org/W2008269062",
    "https://openalex.org/W2009553381",
    "https://openalex.org/W2009913676",
    "https://openalex.org/W2011649969",
    "https://openalex.org/W2021192296",
    "https://openalex.org/W2022816137",
    "https://openalex.org/W2023615889",
    "https://openalex.org/W2023687998",
    "https://openalex.org/W2025613570",
    "https://openalex.org/W2029898749",
    "https://openalex.org/W2030560757",
    "https://openalex.org/W2030864780",
    "https://openalex.org/W2033943361",
    "https://openalex.org/W2034871574",
    "https://openalex.org/W2035622433",
    "https://openalex.org/W2037061138",
    "https://openalex.org/W2037278965",
    "https://openalex.org/W2040553259",
    "https://openalex.org/W2040971876",
    "https://openalex.org/W2044241561",
    "https://openalex.org/W2044542770",
    "https://openalex.org/W2046966583",
    "https://openalex.org/W2047239675",
    "https://openalex.org/W2048130534",
    "https://openalex.org/W2049849397",
    "https://openalex.org/W2053985016",
    "https://openalex.org/W2055386916",
    "https://openalex.org/W2059632047",
    "https://openalex.org/W2065525499",
    "https://openalex.org/W2066218383",
    "https://openalex.org/W2067017838",
    "https://openalex.org/W2067373175",
    "https://openalex.org/W2073266411",
    "https://openalex.org/W2079987638",
    "https://openalex.org/W2080651036",
    "https://openalex.org/W2080981186",
    "https://openalex.org/W2083314087",
    "https://openalex.org/W2084007373",
    "https://openalex.org/W2085039863",
    "https://openalex.org/W2089962605",
    "https://openalex.org/W2094549516",
    "https://openalex.org/W2098923148",
    "https://openalex.org/W2101037833",
    "https://openalex.org/W2101153618",
    "https://openalex.org/W2101524853",
    "https://openalex.org/W2102459772",
    "https://openalex.org/W2104007338",
    "https://openalex.org/W2120161350",
    "https://openalex.org/W2123870375",
    "https://openalex.org/W2123892768",
    "https://openalex.org/W2124958203",
    "https://openalex.org/W2131172255",
    "https://openalex.org/W2131434727",
    "https://openalex.org/W2134868253",
    "https://openalex.org/W2135204261",
    "https://openalex.org/W2138335861",
    "https://openalex.org/W2138597631",
    "https://openalex.org/W2139340966",
    "https://openalex.org/W2142664378",
    "https://openalex.org/W2142678812",
    "https://openalex.org/W2143085832",
    "https://openalex.org/W2143924171",
    "https://openalex.org/W2146536602",
    "https://openalex.org/W2152378246",
    "https://openalex.org/W2152997475",
    "https://openalex.org/W2155113386",
    "https://openalex.org/W2161477597",
    "https://openalex.org/W2161600055",
    "https://openalex.org/W2192016022",
    "https://openalex.org/W2203634181",
    "https://openalex.org/W2214725941",
    "https://openalex.org/W2221669816",
    "https://openalex.org/W2222878407",
    "https://openalex.org/W2255858454",
    "https://openalex.org/W2315752386",
    "https://openalex.org/W2416510212",
    "https://openalex.org/W2418618550",
    "https://openalex.org/W2419150706",
    "https://openalex.org/W2443240960",
    "https://openalex.org/W2444481702",
    "https://openalex.org/W2465178352",
    "https://openalex.org/W2513696712",
    "https://openalex.org/W2517712760",
    "https://openalex.org/W2518386440",
    "https://openalex.org/W2526745866",
    "https://openalex.org/W2562107220",
    "https://openalex.org/W2591727338",
    "https://openalex.org/W2595819286",
    "https://openalex.org/W2604380896",
    "https://openalex.org/W3023896271",
    "https://openalex.org/W4296816736"
  ],
  "related_works": [
    "https://openalex.org/W2011334355",
    "https://openalex.org/W2119040704",
    "https://openalex.org/W2122612215",
    "https://openalex.org/W2606712725",
    "https://openalex.org/W2748952813",
    "https://openalex.org/W2792169531",
    "https://openalex.org/W2899084033",
    "https://openalex.org/W2909307812",
    "https://openalex.org/W3080871630",
    "https://openalex.org/W3145734532"
  ],
  "ngrams_url": "https://api.openalex.org/works/W2792169531/ngrams",
  "abstract_inverted_index": {
    "An": [
      0
    ],
    "increasing": [
      1
    ],
    "number": [
      2
    ],
    "of": [
      3,
      35,
      58,
      78,
      87,
      97,
      132,
      199,
      218,
      233,
      250,
      265,
      275
    ],
    "reports": [
      4
    ],
    "suggest": [
      5
    ],
    "early": [
      6
    ],
    "life": [
      7
    ],
    "exposures": [
      8,
      36,
      59,
      240
    ],
    "result": [
      9
    ],
    "in": [
      10,
      13,
      80,
      186,
      224,
      239
    ],
    "adverse": [
      11
    ],
    "effects": [
      12,
      34,
      281
    ],
    "offspring": [
      14
    ],
    "who": [
      15
    ],
    "were": [
      16,
      155
    ],
    "never": [
      17
    ],
    "directly": [
      18
    ],
    "exposed;": [
      19
    ],
    "this": [
      20,
      50
    ],
    "phenomenon": [
      21,
      51
    ],
    "is": [
      22,
      42,
      52,
      258,
      292
    ],
    "termed": [
      23
    ],
    "\"transgenerational": [
      24
    ],
    "inheritance.\"": [
      25
    ],
    "Given": [
      26
    ],
    "concern": [
      27
    ],
    "for": [
      28,
      32,
      68,
      100,
      119,
      139,
      216,
      252
    ],
    "public": [
      29
    ],
    "health": [
      30,
      123,
      142,
      173
    ],
    "implications": [
      31
    ],
    "potential": [
      33
    ],
    "transmitted": [
      37
    ],
    "to": [
      38,
      44,
      54,
      74,
      84,
      93,
      108,
      247,
      260,
      277
    ],
    "subsequent": [
      39
    ],
    "generations,": [
      40
    ],
    "it": [
      41
    ],
    "critical": [
      43
    ],
    "determine": [
      45
    ],
    "how": [
      46
    ],
    "widespread": [
      47
    ],
    "and": [
      48,
      53,
      60,
      82,
      92,
      110,
      126,
      135,
      157,
      169,
      176,
      208,
      237,
      241,
      263,
      269,
      298
    ],
    "robust": [
      49,
      273
    ],
    "identify": [
      55,
      85
    ],
    "the": [
      56,
      66,
      101,
      112,
      130,
      181,
      187,
      205,
      209
    ],
    "range": [
      57,
      77
    ],
    "possible": [
      61
    ],
    "outcomes.This": [
      62
    ],
    "scoping": [
      63
    ],
    "report": [
      64
    ],
    "examines": [
      65
    ],
    "evidence": [
      67,
      117,
      127,
      162,
      165,
      200,
      228,
      251,
      276,
      294
    ],
    "transgenerational": [
      69,
      102,
      120,
      254,
      280
    ],
    "inheritance": [
      70,
      121
    ],
    "associated": [
      71
    ],
    "with": [
      72
    ],
    "exposure": [
      73,
      207
    ],
    "a": [
      75,
      115,
      160
    ],
    "wide": [
      76
    ],
    "stressors": [
      79
    ],
    "humans": [
      81
    ],
    "animals": [
      83
    ],
    "areas": [
      86
    ],
    "consistency,": [
      88
    ],
    "uncertainty,": [
      89
    ],
    "data": [
      90,
      286
    ],
    "gaps,": [
      91
    ],
    "evaluate": [
      94
    ],
    "general": [
      95
    ],
    "risk": [
      96,
      217,
      232,
      264
    ],
    "bias": [
      98,
      219,
      266
    ],
    "issues": [
      99,
      223,
      267
    ],
    "study": [
      103
    ],
    "design.A": [
      104
    ],
    "protocol": [
      105
    ],
    "was": [
      106
    ],
    "developed": [
      107
    ],
    "collect": [
      109
    ],
    "categorize": [
      111
    ],
    "literature": [
      113
    ],
    "into": [
      114,
      159
    ],
    "systematic": [
      116,
      161
    ],
    "map": [
      118,
      163
    ],
    "by": [
      122,
      164,
      284
    ],
    "effects,": [
      124
    ],
    "exposures,": [
      125
    ],
    "streams": [
      128,
      166
    ],
    "following": [
      129
    ],
    "Office": [
      131
    ],
    "Health": [
      133,
      188
    ],
    "Assessment": [
      134,
      189
    ],
    "Translation": [
      136
    ],
    "(OHAT)": [
      137
    ],
    "approach": [
      138
    ],
    "conducting": [
      140
    ],
    "literature-based": [
      141
    ],
    "assessments.A": [
      143
    ],
    "PubMed": [
      144
    ],
    "search": [
      145
    ],
    "yielded": [
      146
    ],
    "63,758": [
      147
    ],
    "unique": [
      148
    ],
    "records": [
      149
    ],
    "from": [
      150,
      180
    ],
    "which": [
      151
    ],
    "257": [
      152
    ],
    "relevant": [
      153
    ],
    "studies": [
      154,
      183,
      203
    ],
    "identified": [
      156
    ],
    "categorized": [
      158
    ],
    "(46": [
      167
    ],
    "human": [
      168
    ],
    "211": [
      170
    ],
    "animal),": [
      171
    ],
    "broad": [
      172
    ],
    "effect": [
      174
    ],
    "categories,": [
      175
    ],
    "exposures.": [
      177
    ],
    "Data": [
      178
    ],
    "extracted": [
      179
    ],
    "individual": [
      182
    ],
    "are": [
      184,
      195
    ],
    "available": [
      185,
      248
    ],
    "Workspace": [
      190
    ],
    "Collaborative": [
      191
    ],
    "(HAWC)": [
      192
    ],
    "program.": [
      193
    ],
    "There": [
      194
    ],
    "relatively": [
      196
    ],
    "few": [
      197,
      235
    ],
    "bodies": [
      198,
      249,
      274
    ],
    "where": [
      201,
      290
    ],
    "multiple": [
      202,
      222
    ],
    "evaluated": [
      204,
      215
    ],
    "same": [
      206,
      210
    ],
    "or": [
      211,
      226
    ],
    "similar": [
      212
    ],
    "outcomes.": [
      213
    ],
    "Studies": [
      214
    ],
    "generally": [
      220
    ],
    "had": [
      221
    ],
    "design": [
      225
    ],
    "conduct.The": [
      227
    ],
    "mapping": [
      229
    ],
    "illustrated": [
      230
    ],
    "that": [
      231
    ],
    "bias,": [
      234
    ],
    "studies,": [
      236
    ],
    "heterogeneity": [
      238
    ],
    "endpoints": [
      242
    ],
    "examined": [
      243
    ],
    "present": [
      244
    ],
    "serious": [
      245
    ],
    "limitations": [
      246
    ],
    "assessing": [
      253
    ],
    "effects.": [
      255
    ],
    "Targeted": [
      256
    ],
    "research": [
      257
    ],
    "suggested": [
      259
    ],
    "addressed": [
      261
    ],
    "inconsistencies": [
      262
    ],
    "identified,": [
      268
    ],
    "thereby": [
      270
    ],
    "establish": [
      271
    ],
    "more": [
      272
    ],
    "critically": [
      278
    ],
    "assess": [
      279
    ],
    "-": [
      282
    ],
    "particularly": [
      283
    ],
    "adding": [
      285
    ],
    "on": [
      287
    ],
    "exposure-outcome": [
      288
    ],
    "pairs": [
      289
    ],
    "there": [
      291
    ],
    "some": [
      293
    ],
    "(i.e.,": [
      295
    ],
    "reproductive,": [
      296
    ],
    "metabolic,": [
      297
    ],
    "neurological": [
      299
    ],
    "effects).": [
      300
    ]
  },
  "cited_by_api_url": "https://api.openalex.org/works?filter=cites:W2792169531",
  "counts_by_year": [
    {
      "year": 2023,
      "cited_by_count": 1
    },
    {
      "year": 2022,
      "cited_by_count": 5
    },
    {
      "year": 2021,
      "cited_by_count": 1
    },
    {
      "year": 2020,
      "cited_by_count": 6
    },
    {
      "year": 2019,
      "cited_by_count": 2
    },
    {
      "year": 2018,
      "cited_by_count": 2
    }
  ],
  "updated_date": "2023-04-10T06:48:45.520409",
  "created_date": "2018-03-29"
}